analysis/__init__.py
analysis/analysis.py
analysis/analysis_runner.py
analysis/preflight.py
analysis/preprocess.py
analysis/process_ptrace.py
analysis/to_df.py
analysis/visualizer.py
calabash_experimenter-0.1.0.dist-info/METADATA
calabash_experimenter-0.1.0.dist-info/WHEEL
calabash_experimenter-0.1.0.dist-info/entry_points.txt
calabash_experimenter/__init__.py
experiment/__init__.py
experiment/metadata.py
experiment/processes_capture.py
experiment/processtrace.bt
experiment/runner.py
experiment/temperature.py
misc/__init__.py
misc/config.py
misc/util.py
calabash_experimenter-0.1.0.dist-info/RECORD
