Metadata-Version: 2.1
Name: calabash-experimenter
Version: 0.1.0
Summary: A software energy experiment orchestrator.
Author-Email: philippsommer27 <philippsommerhalter@gmail.com>
License: MIT
Requires-Python: >=3.10
Requires-Dist: docker>=7
Requires-Dist: pyyaml>=6
Requires-Dist: schema>=0.7.5
Requires-Dist: matplotlib>=3.8.4
Requires-Dist: pandas>=2.2.2
Requires-Dist: numpy>=1.26.4
Requires-Dist: bcc>=0.1.10
Requires-Dist: seaborn>=0.13.2
Requires-Dist: psutil>=6.0.0
Requires-Dist: py-cpuinfo>=9.0.0
Requires-Dist: scipy>=1.14.0
Requires-Dist: click>=8.1.7
